LICENSE
MANIFEST.in
README.md
VERSION
pyproject.toml
setup.cfg
adminlte3/__init__.py
adminlte3/admin.py
adminlte3/apps.py
adminlte3/compat.py
adminlte3/models.py
adminlte3/tests.py
adminlte3/views.py
adminlte3/migrations/__init__.py
adminlte3/static/admin-lte/LICENSE
adminlte3/static/admin-lte/README.md
adminlte3/static/admin-lte/dist/css/adminlte.css
adminlte3/static/admin-lte/dist/css/adminlte.css.map
adminlte3/static/admin-lte/dist/css/adminlte.min.css
adminlte3/static/admin-lte/dist/css/adminlte.min.css.map
adminlte3/static/admin-lte/dist/css/alt/adminlte.components.css
adminlte3/static/admin-lte/dist/css/alt/adminlte.components.css.map
adminlte3/static/admin-lte/dist/css/alt/adminlte.components.min.css
adminlte3/static/admin-lte/dist/css/alt/adminlte.components.min.css.map
adminlte3/static/admin-lte/dist/css/alt/adminlte.core.css
adminlte3/static/admin-lte/dist/css/alt/adminlte.core.css.map
adminlte3/static/admin-lte/dist/css/alt/adminlte.core.min.css
adminlte3/static/admin-lte/dist/css/alt/adminlte.core.min.css.map
adminlte3/static/admin-lte/dist/css/alt/adminlte.extra-components.css
adminlte3/static/admin-lte/dist/css/alt/adminlte.extra-components.css.map
adminlte3/static/admin-lte/dist/css/alt/adminlte.extra-components.min.css
adminlte3/static/admin-lte/dist/css/alt/adminlte.extra-components.min.css.map
adminlte3/static/admin-lte/dist/css/alt/adminlte.pages.css
adminlte3/static/admin-lte/dist/css/alt/adminlte.pages.css.map
adminlte3/static/admin-lte/dist/css/alt/adminlte.pages.min.css
adminlte3/static/admin-lte/dist/css/alt/adminlte.pages.min.css.map
adminlte3/static/admin-lte/dist/css/alt/adminlte.plugins.css
adminlte3/static/admin-lte/dist/css/alt/adminlte.plugins.css.map
adminlte3/static/admin-lte/dist/css/alt/adminlte.plugins.min.css
adminlte3/static/admin-lte/dist/css/alt/adminlte.plugins.min.css.map
adminlte3/static/admin-lte/dist/img/AdminLTELogo.png
adminlte3/static/admin-lte/dist/img/avatar.png
adminlte3/static/admin-lte/dist/img/avatar2.png
django_adminlte3_amigne.egg-info/PKG-INFO
django_adminlte3_amigne.egg-info/SOURCES.txt
django_adminlte3_amigne.egg-info/dependency_links.txt
django_adminlte3_amigne.egg-info/top_level.txt