Metadata-Version: 2.1
Name: django-adminlte3-amigne
Version: 0.1.99
Summary: AdminLTE template packaged for Django
Home-page: https://github.com/amigne/django-adminlte3
Author: Yann Gauteron
Author-email: yann@amigne.ovh
License: MIT
Project-URL: Bug Tracker, https://github.com/amigne/django-adminlte3/issues
Keywords: template django adminlte
Platform: UNKNOWN
Classifier: Development Status :: 3 - Alpha
Classifier: Intended Audience :: Information Technology
Classifier: Framework :: Django
Classifier: Framework :: Django :: 3.0
Classifier: Framework :: Django :: 3.1
Classifier: Programming Language :: Python
Classifier: Programming Language :: Python :: 3
Classifier: Programming Language :: Python :: 3.7
Classifier: Programming Language :: Python :: 3.8
Classifier: Programming Language :: Python :: 3.9
Classifier: Programming Language :: Python :: Implementation :: CPython
Classifier: Topic :: Software Development :: Libraries :: Python Modules
Classifier: License :: OSI Approved :: MIT License
Requires-Python: >=3.7
